MANIFEST.in
setup.py
cos_viewer.egg-info/PKG-INFO
cos_viewer.egg-info/SOURCES.txt
cos_viewer.egg-info/dependency_links.txt
cos_viewer.egg-info/entry_points.txt
cos_viewer.egg-info/not-zip-safe
cos_viewer.egg-info/requires.txt
cos_viewer.egg-info/top_level.txt
src/__init__.py
src/config_manager.py
src/cos_client.py
src/crypto_utils.py
src/main.py
src/migrate_configs.py
src/cos_viewer/__init__.py
src/cos_viewer/app.py
src/cos_viewer/config_form_screen.py
src/cos_viewer/config_screen.py
src/cos_viewer/download_screen.py
src/cos_viewer/events.py
src/cos_viewer/feature_select_screen.py
src/cos_viewer/file_browser_screen.py
src/cos_viewer/file_details_screen.py
src/cos_viewer/local_file_browser_screen.py
src/cos_viewer/message_screen.py
src/cos_viewer/screens.py
src/cos_viewer/upload_screen.py
src/cos_viewer/css/file_browser.css
src/cos_viewer/css/style.css