Metadata-Version: 2.1
Name: cos-viewer
Version: 0.1.7
Summary: A COS viewer application
Author: Your Name
Author-email: your.email@example.com
Classifier: Programming Language :: Python :: 3
Classifier: License :: OSI Approved :: MIT License
Classifier: Operating System :: OS Independent
Requires-Python: >=3.6
Requires-Dist: textual>=0.34.0
Requires-Dist: cos-python-sdk-v5>=1.9.34
Requires-Dist: python-dotenv>=0.19.0
Requires-Dist: pathlib>=1.0.1
Requires-Dist: cryptography>=36.0.1
